Metadata-Version: 1.0
Name: eddiefroufrou-test123
Version: 0.1
Summary: eddiefroufrou_test123
Home-page: UNKNOWN
Author: UNKNOWN
Author-email: UNKNOWN
License: UNKNOWN
Platform: UNKNOWN
